pyssg/__init__.py
pyssg/arg_parser.py
pyssg/builder.py
pyssg/configuration.py
pyssg/custom_logger.py
pyssg/database.py
pyssg/database_entry.py
pyssg/md_parser.py
pyssg/page.py
pyssg/py.typed
pyssg/pyssg.py
pyssg/utils.py
pyssg/yaml_parser.py
pyssg/plt/__init__.py
pyssg/plt/default.yaml
pyssg/plt/index.html
pyssg/plt/mandatory_config.yaml
pyssg/plt/page.html
pyssg/plt/rss.xml
pyssg/plt/sitemap.xml
pyssg/plt/static_config.yaml
pyssg/plt/tag.html
pyssg-0.9.0.dist-info/LICENSE
pyssg-0.9.0.dist-info/METADATA
pyssg-0.9.0.dist-info/WHEEL
pyssg-0.9.0.dist-info/entry_points.txt
pyssg-0.9.0.dist-info/pbr.json
pyssg-0.9.0.dist-info/top_level.txt
pyssg-0.9.0.dist-info/RECORD
