Metadata-Version: 2.1
Name: pyssg
Version: 0.9.0
Summary: A Static Site Generator using markdown files.
Home-page: https://github.com/luevano/pyssg
Author: David Luevano Alvarado
Author-email: david@luevano.xyz
License: GPLv3
Keywords: python,static,site,generator,markdown,website
Classifier: License :: OSI Approved :: GNU General Public License v3 (GPLv3)
Classifier: Operating System :: Unix
Classifier: Programming Language :: Python
Classifier: Programming Language :: Python :: 3
Classifier: Programming Language :: Python :: 3.7
Classifier: Programming Language :: Python :: 3.8
Classifier: Programming Language :: Python :: 3.9
Classifier: Programming Language :: Python :: 3.10
Classifier: Programming Language :: Python :: 3.11
Classifier: Programming Language :: Python :: 3 :: Only
Classifier: Topic :: Communications :: Email :: Filters
Classifier: Topic :: Internet :: WWW/HTTP :: Dynamic Content :: CGI Tools/Libraries
Classifier: Topic :: Internet :: WWW/HTTP :: Site Management
Classifier: Topic :: Software Development :: Documentation
Classifier: Topic :: Software Development :: Libraries :: Python Modules
Classifier: Topic :: Text Processing :: Filters
Classifier: Topic :: Text Processing :: Markup :: HTML
Classifier: Topic :: Text Processing :: Markup :: Markdown
License-File: LICENSE
Requires-Dist: Jinja2 (>=3.1.2)
Requires-Dist: Markdown (>=3.4.1)
Requires-Dist: markdown-checklist (>=0.4.4)
Requires-Dist: MarkupSafe (>=2.1.1)
Requires-Dist: yafg (>=0.3)
Requires-Dist: pymdown-extensions (>=9.9.2)
Requires-Dist: pymdvar (>=1.0.3)
Requires-Dist: PyYAML (>=6.0)
Requires-Dist: validators (>=0.20.0)
